ssb_libtest41/__init__.py
ssb_libtest41/__main__.py
ssb_libtest41/functions.py
ssb_libtest41/py.typed
ssb_libtest41-0.0.1.dist-info/LICENSE
ssb_libtest41-0.0.1.dist-info/METADATA
ssb_libtest41-0.0.1.dist-info/WHEEL
ssb_libtest41-0.0.1.dist-info/entry_points.txt
ssb_libtest41-0.0.1.dist-info/RECORD
